Lab 07/RAM/RAM.vhd

library IEEE;
use IEEE.STD_LOGIC_1164.ALL;
use ieee.numeric_std.all;

entity RAM is
    Port ( WR : in  STD_LOGIC;
           RD : in  STD_LOGIC;
           Addr : in  STD_LOGIC_VECTOR(3 downto 0);
           Reset : in  STD_LOGIC;
           Data_in : in  STD_LOGIC_VECTOR(7 downto 0);
           Data_out : out  STD_LOGIC_VECTOR(7 downto 0);
			  CLK : in STD_LOGIC);
end RAM;

architecture Behavioral of RAM is

type RAM_TYPE is array(0 to 15) of std_logic_vector(7 downto 0);
signal Data : RAM_TYPE;

begin

	process(CLK) begin
		if(CLK = '1' and CLK'event) then
		if(Reset = '0') then
			for item in 0 to 15 loop
				Data(item) <= STD_LOGIC_VECTOR(to_unsigned(item,8));
			end loop;
		elsif(WR = '1') then
			Data(to_integer(unsigned(Addr))) <= Data_in;
		elsif(RD = '1') then
			Data_out <= Data(to_integer(unsigned(Addr)));
		end if;
		end if;
	end process;


end Behavioral;

Lab 7/RAM/RAM_tb.vhd

LIBRARY ieee;
USE ieee.std_logic_1164.ALL;
 
ENTITY RAM_tb IS
END RAM_tb;
 
ARCHITECTURE behavior OF RAM_tb IS 

    COMPONENT RAM
    PORT(
         WR : IN  std_logic;
         RD : IN  std_logic;
         Addr : IN  std_logic_vector(3 downto 0);
         Reset : IN  std_logic;
         Data_in : IN  std_logic_vector(7 downto 0);
         Data_out : OUT  std_logic_vector(7 downto 0)
        );
    END COMPONENT;
    

   --Inputs
   signal WR : std_logic := '0';
   signal RD : std_logic := '0';
   signal Addr : std_logic_vector(3 downto 0) := (others => '0');
   signal Reset : std_logic := '0';
   signal Data_in : std_logic_vector(7 downto 0) := (others => '0');

 	--Outputs
   signal Data_out : std_logic_vector(7 downto 0);
 
BEGIN
 
	-- Instantiate the Unit Under Test (UUT)
   uut: RAM PORT MAP (
          WR => WR,
          RD => RD,
          Addr => Addr,
          Reset => Reset,
          Data_in => Data_in,
          Data_out => Data_out
        );
 

   -- Stimulus process
   stim_proc: process
   begin		
      -- hold reset state for 100 ns.
      wait for 100 ns;
		Reset <= '1';
		wait for 20 ns;
		Reset <= '0';
		wait for 20 ns;
		Reset <= '1';
		wait for 20 ns;
		
		Data_in <= "00110010";
		Addr <= "0000";
		
		WR <= '1';
		wait for 20 ns;
		WR <= '0';
		
		wait for 20 ns;
		
		RD <= '1';
		wait for 20 ns;
		RD <= '0';
		
		wait for 20 ns;
		Data_in <= "11111110";
		Addr <= "1000";
		
		WR <= '1';
		wait for 20 ns;
		WR <= '0';
		
		wait for 20 ns;
		
		Addr <= "1001";
		RD <= '1';
		wait for 20 ns;
		RD <= '0';
		
		wait for 20 ns;
		
		Addr <= "1011";
		RD <= '1';
		wait for 20 ns;
		RD <= '0';
      wait;
   end process;

END;

Lab 7/RAM/out.vcd
$date
  Mon May 06 11:04:41 2024
$end
$version
  GHDL v0
$end
$timescale
  1 fs
$end
$scope module standard $end
$upscope $end
$scope module std_logic_1164 $end
$upscope $end
$scope module numeric_std $end
$upscope $end
$scope module ram_tb $end
$var reg 1 ! wr $end
$var reg 1 " rd $end
$var reg 4 # addr[3:0] $end
$var reg 1 $ reset $end
$var reg 8 % data_in[7:0] $end
$var reg 8 & data_out[7:0] $end
$scope module uut $end
$var reg 1 ' wr $end
$var reg 1 ( rd $end
$var reg 4 ) addr[3:0] $end
$var reg 1 * reset $end
$var reg 8 + data_in[7:0] $end
$var reg 8 , data_out[7:0] $end
$var reg 1 - clk $end
$comment data is not handled $end
$upscope $end
$upscope $end
$enddefinitions $end
#0
0!
0"
b0000 #
0$
b00000000 %
bUUUUUUUU &
0'
0(
b0000 )
0*
b00000000 +
bUUUUUUUU ,
U-
#100000000
1$
1*
#120000000
0$
0*
#140000000
1$
1*
#160000000
1!
b00110010 %
1'
b00110010 +
#180000000
0!
0'
#200000000
1"
1(
#220000000
0"
0(
#240000000
1!
b1000 #
b11111110 %
1'
b1000 )
b11111110 +
#260000000
0!
0'
#280000000
1"
b1001 #
1(
b1001 )
#300000000
0"
0(
#320000000
1"
b1011 #
1(
b1011 )
#340000000
0"
0(
