Lab 07/DUAL RAM/RAM_Dual.vhd
library IEEE;
use IEEE.STD_LOGIC_1164.ALL;
use ieee.numeric_std.all;

entity RAM_DUAL is
    Port ( WR1 : in  STD_LOGIC;
	 WR2 : in  STD_LOGIC;
           RD1 : in  STD_LOGIC;
			  RD2 : in  STD_LOGIC;
           Addr1 : in  STD_LOGIC_VECTOR(3 downto 0);
			  Addr2 : in  STD_LOGIC_VECTOR(3 downto 0);
           Reset : in  STD_LOGIC;
           Data_in1 : in  STD_LOGIC_VECTOR(7 downto 0);
			  Data_in2: in  STD_LOGIC_VECTOR(7 downto 0);
           Data_out1 : out  STD_LOGIC_VECTOR(7 downto 0);
			  Data_out2 : out  STD_LOGIC_VECTOR(7 downto 0);
			  CLK : in STD_LOGIC);
end RAM_DUAL;

architecture Behavioral of RAM_DUAL is

type RAM_TYPE is array(0 to 15) of std_logic_vector(7 downto 0);
signal Data : RAM_TYPE;

begin

	process(CLK) begin
		if(CLK = '1' and CLK'event) then
		if(Reset = '0') then
			for item in 0 to 15 loop
				Data(item) <= STD_LOGIC_VECTOR(to_unsigned(item,8));
			end loop;
			
		else
		if(WR1 = '1') then
			Data(to_integer(unsigned(Addr1))) <= Data_in1;
			end if;
		if(WR2 = '1') then
			Data(to_integer(unsigned(Addr2))) <= Data_in2;
			end if;
		if(RD1 = '1') then
			Data_out1 <= Data(to_integer(unsigned(Addr1)));
			end if;
		if(RD2 = '1') then
			Data_out2 <= Data(to_integer(unsigned(Addr2)));
		end if;
		end if;
		end if;
	end process;

end Behavioral;

Lab 7/DUAL RAM/RAM_Dual_tb.vhd

LIBRARY ieee;
USE ieee.std_logic_1164.ALL;

ENTITY RAM_DUAL_tb IS
END RAM_DUAL_tb;
 
ARCHITECTURE behavior OF RAM_DUAL_tb IS 
 
    -- Component Declaration for the Unit Under Test (UUT)
    COMPONENT RAM_DUAL
    PORT(
         WR1 : IN  std_logic;
         WR2 : IN  std_logic;
         RD1 : IN  std_logic;
         RD2 : IN  std_logic;
         Addr1 : IN  std_logic_vector(3 downto 0);
         Addr2 : IN  std_logic_vector(3 downto 0);
         Reset : IN  std_logic;
         Data_in1 : IN  std_logic_vector(7 downto 0);
         Data_in2 : IN  std_logic_vector(7 downto 0);
         Data_out1 : OUT  std_logic_vector(7 downto 0);
         Data_out2 : OUT  std_logic_vector(7 downto 0);
         CLK : IN  std_logic
        );
    END COMPONENT;
    

   --Inputs
   signal WR1 : std_logic := '0';
   signal WR2 : std_logic := '0';
   signal RD1 : std_logic := '0';
   signal RD2 : std_logic := '0';
   signal Addr1 : std_logic_vector(3 downto 0) := (others => '0');
   signal Addr2 : std_logic_vector(3 downto 0) := (others => '0');
   signal Reset : std_logic := '0';
   signal Data_in1 : std_logic_vector(7 downto 0) := (others => '0');
   signal Data_in2 : std_logic_vector(7 downto 0) := (others => '0');
   signal CLK : std_logic := '0';

 	--Outputs
   signal Data_out1 : std_logic_vector(7 downto 0);
   signal Data_out2 : std_logic_vector(7 downto 0);

   -- Clock period definitions
   constant CLK_period : time := 10 ns;
 
BEGIN
 
	-- Instantiate the Unit Under Test (UUT)
   uut: RAM_DUAL PORT MAP (
          WR1 => WR1,
          WR2 => WR2,
          RD1 => RD1,
          RD2 => RD2,
          Addr1 => Addr1,
          Addr2 => Addr2,
          Reset => Reset,
          Data_in1 => Data_in1,
          Data_in2 => Data_in2,
          Data_out1 => Data_out1,
          Data_out2 => Data_out2,
          CLK => CLK
        );

   -- Clock process definitions
   CLK_process :process
   begin
		CLK <= '0';
		wait for CLK_period/2;
		CLK <= '1';
		wait for CLK_period/2;
   end process;
 

   -- Stimulus process
   stim_proc: process
   begin		
      -- hold reset state for 100 ns.
      wait for 100 ns;	
		Reset <= '1';
		wait for 20 ns;
		Reset <= '0';
		wait for 20 ns;
		Reset <= '1';
		wait for 20 ns;
		
		Data_in1 <= "00110010";
		Addr1 <= "0000";
		
		WR1 <= '1';
		wait for 20 ns;
		WR1 <= '0';
		
		wait for 20 ns;
		
		RD2 <= '1';
		wait for 20 ns;
		RD2 <= '0';
		
		wait for 20 ns;
		Data_in2 <= "11111110";
		Addr2 <= "1001";
		Data_in1 <= "11111111";
		Addr1 <= "0000";
		
		WR2 <= '1';
		WR1 <= '1';
		wait for 20 ns;
		WR2 <= '0';
		WR1 <= '0';
		
		wait for 20 ns;
		
		Addr1 <= "1101";
		RD1 <= '1';
		wait for 20 ns;
		RD1 <= '0';
		
		wait for 20 ns;
		
		Addr2 <= "1001";
		RD2 <= '1';
		wait for 20 ns;
		RD2 <= '0';

      wait for CLK_period*10;

      wait;
   end process;

END;

Lab 07/DUAL RAM/out.vcd
$date
  Mon May 06 10:46:14 2024
$end
$version
  GHDL v0
$end
$timescale
  1 fs
$end
$scope module standard $end
$upscope $end
$scope module std_logic_1164 $end
$upscope $end
$scope module numeric_std $end
$upscope $end
$scope module ram_dual_tb $end
$var reg 1 ! wr1 $end
$var reg 1 " wr2 $end
$var reg 1 # rd1 $end
$var reg 1 $ rd2 $end
$var reg 4 % addr1[3:0] $end
$var reg 4 & addr2[3:0] $end
$var reg 1 ' reset $end
$var reg 8 ( data_in1[7:0] $end
$var reg 8 ) data_in2[7:0] $end
$var reg 1 * clk $end
$var reg 8 + data_out1[7:0] $end
$var reg 8 , data_out2[7:0] $end
$scope module uut $end
$var reg 1 - wr1 $end
$var reg 1 . wr2 $end
$var reg 1 / rd1 $end
$var reg 1 0 rd2 $end
$var reg 4 1 addr1[3:0] $end
$var reg 4 2 addr2[3:0] $end
$var reg 1 3 reset $end
$var reg 8 4 data_in1[7:0] $end
$var reg 8 5 data_in2[7:0] $end
$var reg 8 6 data_out1[7:0] $end
$var reg 8 7 data_out2[7:0] $end
$var reg 1 8 clk $end
$comment data is not handled $end
$upscope $end
$upscope $end
$enddefinitions $end
#0
0!
0"
0#
0$
b0000 %
b0000 &
0'
b00000000 (
b00000000 )
0*
bUUUUUUUU +
bUUUUUUUU ,
0-
0.
0/
00
b0000 1
b0000 2
03
b00000000 4
b00000000 5
bUUUUUUUU 6
bUUUUUUUU 7
08
#5000000
1*
18
#10000000
0*
08
#15000000
1*
18
#20000000
0*
08
#25000000
1*
18
#30000000
0*
08
#35000000
1*
18
#40000000
0*
08
#45000000
1*
18
#50000000
0*
08
#55000000
1*
18
#60000000
0*
08
#65000000
1*
18
#70000000
0*
08
#75000000
1*
18
#80000000
0*
08
#85000000
1*
18
#90000000
0*
08
#95000000
1*
18
#100000000
1'
0*
13
08
#105000000
1*
18
#110000000
0*
08
#115000000
1*
18
#120000000
0'
0*
03
08
#125000000
1*
18
#130000000
0*
08
#135000000
1*
18
#140000000
1'
0*
13
08
#145000000
1*
18
#150000000
0*
08
#155000000
1*
18
#160000000
1!
b00110010 (
0*
1-
b00110010 4
08
#165000000
1*
18
#170000000
0*
08
#175000000
1*
18
#180000000
0!
0*
0-
08
#185000000
1*
18
#190000000
0*
08
#195000000
1*
18
#200000000
1$
0*
10
08
#205000000
1*
b00110010 ,
b00110010 7
18
#210000000
0*
08
#215000000
1*
18
#220000000
0$
0*
00
08
#225000000
1*
18
#230000000
0*
08
#235000000
1*
18
#240000000
1!
1"
b1001 &
b11111111 (
b11111110 )
0*
1-
1.
b1001 2
b11111111 4
b11111110 5
08
#245000000
1*
18
#250000000
0*
08
#255000000
1*
18
#260000000
0!
0"
0*
0-
0.
08
#265000000
1*
18
#270000000
0*
08
#275000000
1*
18
#280000000
1#
b1101 %
0*
1/
b1101 1
08
#285000000
1*
b00001101 +
b00001101 6
18
#290000000
0*
08
#295000000
1*
18
#300000000
0#
0*
0/
08
#305000000
1*
18
#310000000
0*
08
#315000000
1*
18
#320000000
1$
0*
10
08
#325000000
1*
b11111110 ,
b11111110 7
18
#330000000
0*
08
#335000000
1*
18
#340000000
0$
0*
00
08
