Lab 3/RippleCounter4Bit/TFF.vhd

library IEEE;
use IEEE.STD_LOGIC_1164.ALL;


entity TFF is
    Port ( T : in  STD_LOGIC;
           rst : in  STD_LOGIC;
           clk : in  STD_LOGIC;
           Q : out  STD_LOGIC);
end TFF;

architecture Behavioral of TFF is
signal t_temp : std_logic;
begin

	process(clk,rst)begin
		if(rst = '1')then
			t_temp <= '0';
		elsif(clk = '0' and clk'event and T = '1')then
			t_temp <= not t_temp;
		end if;
	end process;
Q <= t_temp;

end Behavioral;

Lab 3/RippleCounter4Bit/FreqDivider.vhd

library IEEE;
use IEEE.STD_LOGIC_1164.ALL;


entity FreqDivider is
    Port ( clk_in : in  STD_LOGIC;
           clk_out : out  STD_LOGIC);
end FreqDivider;

architecture Behavioral of FreqDivider is

signal count : integer := 1;
signal clk_tmp : std_logic := '0';

begin

	process(clk_in) begin
		if(clk_in = '0' and clk_in'event) then
			count <= count + 1;
			if(count = 10) then
				clk_tmp <= not clk_tmp;
				count <= 1;
			end if;
		end if;
	end process;
	
	clk_out <= clk_tmp;

end Behavioral;

Lab 3/RippleCounter4Bit/RippleCounter4b.vhd

library IEEE;
use IEEE.STD_LOGIC_1164.ALL;


entity RippleCounter4b is
    Port ( clk : in  STD_LOGIC;
			  rst : in STD_LOGIC;
           Output_r : out  STD_LOGIC_VECTOR(3 downto 0));
end RippleCounter4b;

architecture Behavioral of RippleCounter4b is

component TFF is
	Port ( T : in  STD_LOGIC;
           rst : in  STD_LOGIC;
           clk : in  STD_LOGIC;
           Q : out  STD_LOGIC);
end component;

component FreqDivider is
    Port ( clk_in : in  STD_LOGIC;
           clk_out : out  STD_LOGIC);
end component;

signal clks : std_logic_vector(2 downto 0);
signal clk_out : std_logic;

begin
	frqd: FreqDivider port map(clk_in => clk, clk_out => clk_out);

	tff0: TFF port map(T => '1', rst => rst, clk => clk_out, Q => clks(0));
	tff1: TFF port map(T => '1', rst => rst, clk => clks(0), Q => clks(1));
	tff2: TFF port map(T => '1', rst => rst, clk => clks(1), Q => clks(2));
	tff3: TFF port map(T => '1', rst => rst, clk => clks(2), Q => Output_r(3));

	Output_r(0) <= clks(0);
	Output_r(1) <= clks(1);
	Output_r(2) <= clks(2);
end Behavioral;

Lab 3/RippleCounter4Bit/RippleCounter4b_tb.vhd

LIBRARY ieee;
USE ieee.std_logic_1164.ALL;
 
ENTITY RippleCounter4b_tb IS
END RippleCounter4b_tb;
 
ARCHITECTURE behavior OF RippleCounter4b_tb IS 
 
    -- Component Declaration for the Unit Under Test (UUT)
 
    COMPONENT RippleCounter4b
    PORT(
         clk : IN  std_logic;
         rst : IN  std_logic;
         Output_r : OUT  std_logic_vector(3 downto 0)
        );
    END COMPONENT;
    

   --Inputs
   signal clk : std_logic := '0';
   signal rst : std_logic := '1';

 	--Outputs
   signal Output_r : std_logic_vector(3 downto 0);

   -- -- Clock period definitions
   constant clk_period : time := 1 ns;

BEGIN
 
	-- Instantiate the Unit Under Test (UUT)
   uut: RippleCounter4b PORT MAP (
          clk => clk,
          rst => rst,
          Output_r => Output_r
        );

   --Clock process definitions
   clk_process :process
   begin
		clk <= '0';
		wait for clk_period/2;
		clk <= '1';
		wait for clk_period/2;
   end process;

   -- Stimulus process
   stim_proc: process
   begin		
      -- hold reset state for 100 ns.
      
      wait for 100 ns;	
		rst <= '0';
   
      wait for clk_period*10;

      -- insert stimulus here 

      wait;
   end process stim_proc;

END;

Lab 3/RippleCounter4Bit/out.vcd
$date
  Sun Mar 10 23:26:21 2024
$end
$version
  GHDL v0
$end
$timescale
  1 fs
$end
$scope module standard $end
$upscope $end
$scope module std_logic_1164 $end
$upscope $end
$scope module ripplecounter4b_tb $end
$var reg 1 ! clk $end
$var reg 1 " rst $end
$var reg 4 # output_r[3:0] $end
$scope module uut $end
$var reg 1 $ clk $end
$var reg 1 % rst $end
$var reg 4 & output_r[3:0] $end
$var reg 3 ' clks[2:0] $end
$var reg 1 ( clk_out $end
$scope module frqd $end
$var reg 1 ) clk_in $end
$var reg 1 * clk_out $end
$var integer 32 + count $end
$var reg 1 , clk_tmp $end
$upscope $end
$scope module tff0 $end
$var reg 1 - t $end
$var reg 1 . rst $end
$var reg 1 / clk $end
$var reg 1 0 q $end
$var reg 1 1 t_temp $end
$upscope $end
$scope module tff1 $end
$var reg 1 2 t $end
$var reg 1 3 rst $end
$var reg 1 4 clk $end
$var reg 1 5 q $end
$var reg 1 6 t_temp $end
$upscope $end
$scope module tff2 $end
$var reg 1 7 t $end
$var reg 1 8 rst $end
$var reg 1 9 clk $end
$var reg 1 : q $end
$var reg 1 ; t_temp $end
$upscope $end
$scope module tff3 $end
$var reg 1 < t $end
$var reg 1 = rst $end
$var reg 1 > clk $end
$var reg 1 ? q $end
$var reg 1 @ t_temp $end
$upscope $end
$upscope $end
$upscope $end
$enddefinitions $end
#0
0!
1"
b0000 #
0$
1%
b0000 &
b000 '
0(
0)
0*
b1 +
0,
1-
1.
0/
00
01
12
13
04
05
06
17
18
09
0:
0;
1<
1=
0>
0?
0@
#500000
1!
1$
1)
#1000000
0!
0$
0)
b10 +
#1500000
1!
1$
1)
#2000000
0!
0$
0)
b11 +
#2500000
1!
1$
1)
#3000000
0!
0$
0)
b100 +
#3500000
1!
1$
1)
#4000000
0!
0$
0)
b101 +
#4500000
1!
1$
1)
#5000000
0!
0$
0)
b110 +
#5500000
1!
1$
1)
#6000000
0!
0$
0)
b111 +
#6500000
1!
1$
1)
#7000000
0!
0$
0)
b1000 +
#7500000
1!
1$
1)
#8000000
0!
0$
0)
b1001 +
#8500000
1!
1$
1)
#9000000
0!
0$
0)
b1010 +
#9500000
1!
1$
1)
#10000000
0!
0$
1(
0)
1*
b1 +
1,
1/
#10500000
1!
1$
1)
#11000000
0!
0$
0)
b10 +
#11500000
1!
1$
1)
#12000000
0!
0$
0)
b11 +
#12500000
1!
1$
1)
#13000000
0!
0$
0)
b100 +
#13500000
1!
1$
1)
#14000000
0!
0$
0)
b101 +
#14500000
1!
1$
1)
#15000000
0!
0$
0)
b110 +
#15500000
1!
1$
1)
#16000000
0!
0$
0)
b111 +
#16500000
1!
1$
1)
#17000000
0!
0$
0)
b1000 +
#17500000
1!
1$
1)
#18000000
0!
0$
0)
b1001 +
#18500000
1!
1$
1)
#19000000
0!
0$
0)
b1010 +
#19500000
1!
1$
1)
#20000000
0!
0$
0(
0)
0*
b1 +
0,
0/
#20500000
1!
1$
1)
#21000000
0!
0$
0)
b10 +
#21500000
1!
1$
1)
#22000000
0!
0$
0)
b11 +
#22500000
1!
1$
1)
#23000000
0!
0$
0)
b100 +
#23500000
1!
1$
1)
#24000000
0!
0$
0)
b101 +
#24500000
1!
1$
1)
#25000000
0!
0$
0)
b110 +
#25500000
1!
1$
1)
#26000000
0!
0$
0)
b111 +
#26500000
1!
1$
1)
#27000000
0!
0$
0)
b1000 +
#27500000
1!
1$
1)
#28000000
0!
0$
0)
b1001 +
#28500000
1!
1$
1)
#29000000
0!
0$
0)
b1010 +
#29500000
1!
1$
1)
#30000000
0!
0$
1(
0)
1*
b1 +
1,
1/
#30500000
1!
1$
1)
#31000000
0!
0$
0)
b10 +
#31500000
1!
1$
1)
#32000000
0!
0$
0)
b11 +
#32500000
1!
1$
1)
#33000000
0!
0$
0)
b100 +
#33500000
1!
1$
1)
#34000000
0!
0$
0)
b101 +
#34500000
1!
1$
1)
#35000000
0!
0$
0)
b110 +
#35500000
1!
1$
1)
#36000000
0!
0$
0)
b111 +
#36500000
1!
1$
1)
#37000000
0!
0$
0)
b1000 +
#37500000
1!
1$
1)
#38000000
0!
0$
0)
b1001 +
#38500000
1!
1$
1)
#39000000
0!
0$
0)
b1010 +
#39500000
1!
1$
1)
#40000000
0!
0$
0(
0)
0*
b1 +
0,
0/
#40500000
1!
1$
1)
#41000000
0!
0$
0)
b10 +
#41500000
1!
1$
1)
#42000000
0!
0$
0)
b11 +
#42500000
1!
1$
1)
#43000000
0!
0$
0)
b100 +
#43500000
1!
1$
1)
#44000000
0!
0$
0)
b101 +
#44500000
1!
1$
1)
#45000000
0!
0$
0)
b110 +
#45500000
1!
1$
1)
#46000000
0!
0$
0)
b111 +
#46500000
1!
1$
1)
#47000000
0!
0$
0)
b1000 +
#47500000
1!
1$
1)
#48000000
0!
0$
0)
b1001 +
#48500000
1!
1$
1)
#49000000
0!
0$
0)
b1010 +
#49500000
1!
1$
1)
#50000000
0!
0$
1(
0)
1*
b1 +
1,
1/
#50500000
1!
1$
1)
#51000000
0!
0$
0)
b10 +
#51500000
1!
1$
1)
#52000000
0!
0$
0)
b11 +
#52500000
1!
1$
1)
#53000000
0!
0$
0)
b100 +
#53500000
1!
1$
1)
#54000000
0!
0$
0)
b101 +
#54500000
1!
1$
1)
#55000000
0!
0$
0)
b110 +
#55500000
1!
1$
1)
#56000000
0!
0$
0)
b111 +
#56500000
1!
1$
1)
#57000000
0!
0$
0)
b1000 +
#57500000
1!
1$
1)
#58000000
0!
0$
0)
b1001 +
#58500000
1!
1$
1)
#59000000
0!
0$
0)
b1010 +
#59500000
1!
1$
1)
#60000000
0!
0$
0(
0)
0*
b1 +
0,
0/
#60500000
1!
1$
1)
#61000000
0!
0$
0)
b10 +
#61500000
1!
1$
1)
#62000000
0!
0$
0)
b11 +
#62500000
1!
1$
1)
#63000000
0!
0$
0)
b100 +
#63500000
1!
1$
1)
#64000000
0!
0$
0)
b101 +
#64500000
1!
1$
1)
#65000000
0!
0$
0)
b110 +
#65500000
1!
1$
1)
#66000000
0!
0$
0)
b111 +
#66500000
1!
1$
1)
#67000000
0!
0$
0)
b1000 +
#67500000
1!
1$
1)
#68000000
0!
0$
0)
b1001 +
#68500000
1!
1$
1)
#69000000
0!
0$
0)
b1010 +
#69500000
1!
1$
1)
#70000000
0!
0$
1(
0)
1*
b1 +
1,
1/
#70500000
1!
1$
1)
#71000000
0!
0$
0)
b10 +
#71500000
1!
1$
1)
#72000000
0!
0$
0)
b11 +
#72500000
1!
1$
1)
#73000000
0!
0$
0)
b100 +
#73500000
1!
1$
1)
#74000000
0!
0$
0)
b101 +
#74500000
1!
1$
1)
#75000000
0!
0$
0)
b110 +
#75500000
1!
1$
1)
#76000000
0!
0$
0)
b111 +
#76500000
1!
1$
1)
#77000000
0!
0$
0)
b1000 +
#77500000
1!
1$
1)
#78000000
0!
0$
0)
b1001 +
#78500000
1!
1$
1)
#79000000
0!
0$
0)
b1010 +
#79500000
1!
1$
1)
#80000000
0!
0$
0(
0)
0*
b1 +
0,
0/
#80500000
1!
1$
1)
#81000000
0!
0$
0)
b10 +
#81500000
1!
1$
1)
#82000000
0!
0$
0)
b11 +
#82500000
1!
1$
1)
#83000000
0!
0$
0)
b100 +
#83500000
1!
1$
1)
#84000000
0!
0$
0)
b101 +
#84500000
1!
1$
1)
#85000000
0!
0$
0)
b110 +
#85500000
1!
1$
1)
#86000000
0!
0$
0)
b111 +
#86500000
1!
1$
1)
#87000000
0!
0$
0)
b1000 +
#87500000
1!
1$
1)
#88000000
0!
0$
0)
b1001 +
#88500000
1!
1$
1)
#89000000
0!
0$
0)
b1010 +
#89500000
1!
1$
1)
#90000000
0!
0$
1(
0)
1*
b1 +
1,
1/
#90500000
1!
1$
1)
#91000000
0!
0$
0)
b10 +
#91500000
1!
1$
1)
#92000000
0!
0$
0)
b11 +
#92500000
1!
1$
1)
#93000000
0!
0$
0)
b100 +
#93500000
1!
1$
1)
#94000000
0!
0$
0)
b101 +
#94500000
1!
1$
1)
#95000000
0!
0$
0)
b110 +
#95500000
1!
1$
1)
#96000000
0!
0$
0)
b111 +
#96500000
1!
1$
1)
#97000000
0!
0$
0)
b1000 +
#97500000
1!
1$
1)
#98000000
0!
0$
0)
b1001 +
#98500000
1!
1$
1)
#99000000
0!
0$
0)
b1010 +
#99500000
1!
1$
1)
#100000000
0!
0"
b0001 #
0$
0%
b0001 &
b001 '
0(
0)
0*
b1 +
0,
0.
0/
10
11
03
14
08
0=
#100500000
1!
1$
1)
#101000000
0!
0$
0)
b10 +
#101500000
1!
1$
1)
#102000000
0!
0$
0)
b11 +
#102500000
1!
1$
1)
#103000000
0!
0$
0)
b100 +
#103500000
1!
1$
1)
#104000000
0!
0$
0)
b101 +
#104500000
1!
1$
1)
#105000000
0!
0$
0)
b110 +
#105500000
1!
1$
1)
#106000000
0!
0$
0)
b111 +
#106500000
1!
1$
1)
#107000000
0!
0$
0)
b1000 +
#107500000
1!
1$
1)
#108000000
0!
0$
0)
b1001 +
#108500000
1!
1$
1)
#109000000
0!
0$
0)
b1010 +
#109500000
1!
1$
1)
#110000000
0!
0$
1(
0)
1*
b1 +
1,
1/
#110500000
1!
1$
1)
#111000000
0!
0$
0)
b10 +
#111500000
1!
1$
1)
#112000000
0!
0$
0)
b11 +
#112500000
1!
1$
1)
#113000000
0!
0$
0)
b100 +
#113500000
1!
1$
1)
#114000000
0!
0$
0)
b101 +
#114500000
1!
1$
1)
#115000000
0!
0$
0)
b110 +
#115500000
1!
1$
1)
#116000000
0!
0$
0)
b111 +
#116500000
1!
1$
1)
#117000000
0!
0$
0)
b1000 +
#117500000
1!
1$
1)
#118000000
0!
0$
0)
b1001 +
#118500000
1!
1$
1)
#119000000
0!
0$
0)
b1010 +
#119500000
1!
1$
1)
#120000000
0!
b0010 #
0$
b0010 &
b010 '
0(
0)
0*
b1 +
0,
0/
00
01
04
15
16
19
#120500000
1!
1$
1)
#121000000
0!
0$
0)
b10 +
#121500000
1!
1$
1)
#122000000
0!
0$
0)
b11 +
#122500000
1!
1$
1)
#123000000
0!
0$
0)
b100 +
#123500000
1!
1$
1)
#124000000
0!
0$
0)
b101 +
#124500000
1!
1$
1)
#125000000
0!
0$
0)
b110 +
#125500000
1!
1$
1)
#126000000
0!
0$
0)
b111 +
#126500000
1!
1$
1)
#127000000
0!
0$
0)
b1000 +
#127500000
1!
1$
1)
#128000000
0!
0$
0)
b1001 +
#128500000
1!
1$
1)
#129000000
0!
0$
0)
b1010 +
#129500000
1!
1$
1)
#130000000
0!
0$
1(
0)
1*
b1 +
1,
1/
#130500000
1!
1$
1)
#131000000
0!
0$
0)
b10 +
#131500000
1!
1$
1)
#132000000
0!
0$
0)
b11 +
#132500000
1!
1$
1)
#133000000
0!
0$
0)
b100 +
#133500000
1!
1$
1)
#134000000
0!
0$
0)
b101 +
#134500000
1!
1$
1)
#135000000
0!
0$
0)
b110 +
#135500000
1!
1$
1)
#136000000
0!
0$
0)
b111 +
#136500000
1!
1$
1)
#137000000
0!
0$
0)
b1000 +
#137500000
1!
1$
1)
#138000000
0!
0$
0)
b1001 +
#138500000
1!
1$
1)
#139000000
0!
0$
0)
b1010 +
#139500000
1!
1$
1)
#140000000
0!
b0011 #
0$
b0011 &
b011 '
0(
0)
0*
b1 +
0,
0/
10
11
14
#140500000
1!
1$
1)
#141000000
0!
0$
0)
b10 +
#141500000
1!
1$
1)
#142000000
0!
0$
0)
b11 +
#142500000
1!
1$
1)
#143000000
0!
0$
0)
b100 +
#143500000
1!
1$
1)
#144000000
0!
0$
0)
b101 +
#144500000
1!
1$
1)
#145000000
0!
0$
0)
b110 +
#145500000
1!
1$
1)
#146000000
0!
0$
0)
b111 +
#146500000
1!
1$
1)
#147000000
0!
0$
0)
b1000 +
#147500000
1!
1$
1)
#148000000
0!
0$
0)
b1001 +
#148500000
1!
1$
1)
#149000000
0!
0$
0)
b1010 +
#149500000
1!
1$
1)
#150000000
0!
0$
1(
0)
1*
b1 +
1,
1/
#150500000
1!
1$
1)
#151000000
0!
0$
0)
b10 +
#151500000
1!
1$
1)
#152000000
0!
0$
0)
b11 +
#152500000
1!
1$
1)
#153000000
0!
0$
0)
b100 +
#153500000
1!
1$
1)
#154000000
0!
0$
0)
b101 +
#154500000
1!
1$
1)
#155000000
0!
0$
0)
b110 +
#155500000
1!
1$
1)
#156000000
0!
0$
0)
b111 +
#156500000
1!
1$
1)
#157000000
0!
0$
0)
b1000 +
#157500000
1!
1$
1)
#158000000
0!
0$
0)
b1001 +
#158500000
1!
1$
1)
#159000000
0!
0$
0)
b1010 +
#159500000
1!
1$
1)
#160000000
0!
b0100 #
0$
b0100 &
b100 '
0(
0)
0*
b1 +
0,
0/
00
01
04
05
06
09
1:
1;
1>
#160500000
1!
1$
1)
#161000000
0!
0$
0)
b10 +
#161500000
1!
1$
1)
#162000000
0!
0$
0)
b11 +
#162500000
1!
1$
1)
#163000000
0!
0$
0)
b100 +
#163500000
1!
1$
1)
#164000000
0!
0$
0)
b101 +
#164500000
1!
1$
1)
#165000000
0!
0$
0)
b110 +
#165500000
1!
1$
1)
#166000000
0!
0$
0)
b111 +
#166500000
1!
1$
1)
#167000000
0!
0$
0)
b1000 +
#167500000
1!
1$
1)
#168000000
0!
0$
0)
b1001 +
#168500000
1!
1$
1)
#169000000
0!
0$
0)
b1010 +
#169500000
1!
1$
1)
#170000000
0!
0$
1(
0)
1*
b1 +
1,
1/
#170500000
1!
1$
1)
#171000000
0!
0$
0)
b10 +
#171500000
1!
1$
1)
#172000000
0!
0$
0)
b11 +
#172500000
1!
1$
1)
#173000000
0!
0$
0)
b100 +
#173500000
1!
1$
1)
#174000000
0!
0$
0)
b101 +
#174500000
1!
1$
1)
#175000000
0!
0$
0)
b110 +
#175500000
1!
1$
1)
#176000000
0!
0$
0)
b111 +
#176500000
1!
1$
1)
#177000000
0!
0$
0)
b1000 +
#177500000
1!
1$
1)
#178000000
0!
0$
0)
b1001 +
#178500000
1!
1$
1)
#179000000
0!
0$
0)
b1010 +
#179500000
1!
1$
1)
#180000000
0!
b0101 #
0$
b0101 &
b101 '
0(
0)
0*
b1 +
0,
0/
10
11
14
#180500000
1!
1$
1)
#181000000
0!
0$
0)
b10 +
#181500000
1!
1$
1)
#182000000
0!
0$
0)
b11 +
#182500000
1!
1$
1)
#183000000
0!
0$
0)
b100 +
#183500000
1!
1$
1)
#184000000
0!
0$
0)
b101 +
#184500000
1!
1$
1)
#185000000
0!
0$
0)
b110 +
#185500000
1!
1$
1)
#186000000
0!
0$
0)
b111 +
#186500000
1!
1$
1)
#187000000
0!
0$
0)
b1000 +
#187500000
1!
1$
1)
#188000000
0!
0$
0)
b1001 +
#188500000
1!
1$
1)
#189000000
0!
0$
0)
b1010 +
#189500000
1!
1$
1)
#190000000
0!
0$
1(
0)
1*
b1 +
1,
1/
#190500000
1!
1$
1)
#191000000
0!
0$
0)
b10 +
#191500000
1!
1$
1)
#192000000
0!
0$
0)
b11 +
#192500000
1!
1$
1)
#193000000
0!
0$
0)
b100 +
#193500000
1!
1$
1)
#194000000
0!
0$
0)
b101 +
#194500000
1!
1$
1)
#195000000
0!
0$
0)
b110 +
#195500000
1!
1$
1)
#196000000
0!
0$
0)
b111 +
#196500000
1!
1$
1)
#197000000
0!
0$
0)
b1000 +
#197500000
1!
1$
1)
#198000000
0!
0$
0)
b1001 +
#198500000
1!
1$
1)
#199000000
0!
0$
0)
b1010 +
#199500000
1!
1$
1)
#200000000
0!
b0110 #
0$
b0110 &
b110 '
0(
0)
0*
b1 +
0,
0/
00
01
04
15
16
19
#200500000
1!
1$
1)
#201000000
0!
0$
0)
b10 +
#201500000
1!
1$
1)
#202000000
0!
0$
0)
b11 +
#202500000
1!
1$
1)
#203000000
0!
0$
0)
b100 +
#203500000
1!
1$
1)
#204000000
0!
0$
0)
b101 +
#204500000
1!
1$
1)
#205000000
0!
0$
0)
b110 +
#205500000
1!
1$
1)
#206000000
0!
0$
0)
b111 +
#206500000
1!
1$
1)
#207000000
0!
0$
0)
b1000 +
#207500000
1!
1$
1)
#208000000
0!
0$
0)
b1001 +
#208500000
1!
1$
1)
#209000000
0!
0$
0)
b1010 +
#209500000
1!
1$
1)
#210000000
0!
0$
1(
0)
1*
b1 +
1,
1/
#210500000
1!
1$
1)
#211000000
0!
0$
0)
b10 +
#211500000
1!
1$
1)
#212000000
0!
0$
0)
b11 +
#212500000
1!
1$
1)
#213000000
0!
0$
0)
b100 +
#213500000
1!
1$
1)
#214000000
0!
0$
0)
b101 +
#214500000
1!
1$
1)
#215000000
0!
0$
0)
b110 +
#215500000
1!
1$
1)
#216000000
0!
0$
0)
b111 +
#216500000
1!
1$
1)
#217000000
0!
0$
0)
b1000 +
#217500000
1!
1$
1)
#218000000
0!
0$
0)
b1001 +
#218500000
1!
1$
1)
#219000000
0!
0$
0)
b1010 +
#219500000
1!
1$
1)
#220000000
0!
b0111 #
0$
b0111 &
b111 '
0(
0)
0*
b1 +
0,
0/
10
11
14
#220500000
1!
1$
1)
#221000000
0!
0$
0)
b10 +
#221500000
1!
1$
1)
#222000000
0!
0$
0)
b11 +
#222500000
1!
1$
1)
#223000000
0!
0$
0)
b100 +
#223500000
1!
1$
1)
#224000000
0!
0$
0)
b101 +
#224500000
1!
1$
1)
#225000000
0!
0$
0)
b110 +
#225500000
1!
1$
1)
#226000000
0!
0$
0)
b111 +
#226500000
1!
1$
1)
#227000000
0!
0$
0)
b1000 +
#227500000
1!
1$
1)
#228000000
0!
0$
0)
b1001 +
#228500000
1!
1$
1)
#229000000
0!
0$
0)
b1010 +
#229500000
1!
1$
1)
#230000000
0!
0$
1(
0)
1*
b1 +
1,
1/
#230500000
1!
1$
1)
#231000000
0!
0$
0)
b10 +
#231500000
1!
1$
1)
#232000000
0!
0$
0)
b11 +
#232500000
1!
1$
1)
#233000000
0!
0$
0)
b100 +
#233500000
1!
1$
1)
#234000000
0!
0$
0)
b101 +
#234500000
1!
1$
1)
#235000000
0!
0$
0)
b110 +
#235500000
1!
1$
1)
#236000000
0!
0$
0)
b111 +
#236500000
1!
1$
1)
#237000000
0!
0$
0)
b1000 +
#237500000
1!
1$
1)
#238000000
0!
0$
0)
b1001 +
#238500000
1!
1$
1)
#239000000
0!
0$
0)
b1010 +
#239500000
1!
1$
1)
#240000000
0!
b1000 #
0$
b1000 &
b000 '
0(
0)
0*
b1 +
0,
0/
00
01
04
05
06
09
0:
0;
0>
1?
1@
#240500000
1!
1$
1)
#241000000
0!
0$
0)
b10 +
#241500000
1!
1$
1)
#242000000
0!
0$
0)
b11 +
#242500000
1!
1$
1)
#243000000
0!
0$
0)
b100 +
#243500000
1!
1$
1)
#244000000
0!
0$
0)
b101 +
#244500000
1!
1$
1)
#245000000
0!
0$
0)
b110 +
#245500000
1!
1$
1)
#246000000
0!
0$
0)
b111 +
#246500000
1!
1$
1)
#247000000
0!
0$
0)
b1000 +
#247500000
1!
1$
1)
#248000000
0!
0$
0)
b1001 +
#248500000
1!
1$
1)
#249000000
0!
0$
0)
b1010 +
#249500000
1!
1$
1)
#250000000
0!
0$
1(
0)
1*
b1 +
1,
1/
#250500000
1!
1$
1)
#251000000
0!
0$
0)
b10 +
#251500000
1!
1$
1)
#252000000
0!
0$
0)
b11 +
#252500000
1!
1$
1)
#253000000
0!
0$
0)
b100 +
#253500000
1!
1$
1)
#254000000
0!
0$
0)
b101 +
#254500000
1!
1$
1)
#255000000
0!
0$
0)
b110 +
#255500000
1!
1$
1)
#256000000
0!
0$
0)
b111 +
#256500000
1!
1$
1)
#257000000
0!
0$
0)
b1000 +
#257500000
1!
1$
1)
#258000000
0!
0$
0)
b1001 +
#258500000
1!
1$
1)
#259000000
0!
0$
0)
b1010 +
#259500000
1!
1$
1)
#260000000
0!
b1001 #
0$
b1001 &
b001 '
0(
0)
0*
b1 +
0,
0/
10
11
14
#260500000
1!
1$
1)
#261000000
0!
0$
0)
b10 +
#261500000
1!
1$
1)
#262000000
0!
0$
0)
b11 +
#262500000
1!
1$
1)
#263000000
0!
0$
0)
b100 +
#263500000
1!
1$
1)
#264000000
0!
0$
0)
b101 +
#264500000
1!
1$
1)
#265000000
0!
0$
0)
b110 +
#265500000
1!
1$
1)
#266000000
0!
0$
0)
b111 +
#266500000
1!
1$
1)
#267000000
0!
0$
0)
b1000 +
#267500000
1!
1$
1)
#268000000
0!
0$
0)
b1001 +
#268500000
1!
1$
1)
#269000000
0!
0$
0)
b1010 +
#269500000
1!
1$
1)
#270000000
0!
0$
1(
0)
1*
b1 +
1,
1/
#270500000
1!
1$
1)
#271000000
0!
0$
0)
b10 +
#271500000
1!
1$
1)
#272000000
0!
0$
0)
b11 +
#272500000
1!
1$
1)
#273000000
0!
0$
0)
b100 +
#273500000
1!
1$
1)
#274000000
0!
0$
0)
b101 +
#274500000
1!
1$
1)
#275000000
0!
0$
0)
b110 +
#275500000
1!
1$
1)
#276000000
0!
0$
0)
b111 +
#276500000
1!
1$
1)
#277000000
0!
0$
0)
b1000 +
#277500000
1!
1$
1)
#278000000
0!
0$
0)
b1001 +
#278500000
1!
1$
1)
#279000000
0!
0$
0)
b1010 +
#279500000
1!
1$
1)
#280000000
0!
b1010 #
0$
b1010 &
b010 '
0(
0)
0*
b1 +
0,
0/
00
01
04
15
16
19
#280500000
1!
1$
1)
#281000000
0!
0$
0)
b10 +
#281500000
1!
1$
1)
#282000000
0!
0$
0)
b11 +
#282500000
1!
1$
1)
#283000000
0!
0$
0)
b100 +
#283500000
1!
1$
1)
#284000000
0!
0$
0)
b101 +
#284500000
1!
1$
1)
#285000000
0!
0$
0)
b110 +
#285500000
1!
1$
1)
#286000000
0!
0$
0)
b111 +
#286500000
1!
1$
1)
#287000000
0!
0$
0)
b1000 +
#287500000
1!
1$
1)
#288000000
0!
0$
0)
b1001 +
#288500000
1!
1$
1)
#289000000
0!
0$
0)
b1010 +
#289500000
1!
1$
1)
#290000000
0!
0$
1(
0)
1*
b1 +
1,
1/
#290500000
1!
1$
1)
#291000000
0!
0$
0)
b10 +
#291500000
1!
1$
1)
#292000000
0!
0$
0)
b11 +
#292500000
1!
1$
1)
#293000000
0!
0$
0)
b100 +
#293500000
1!
1$
1)
#294000000
0!
0$
0)
b101 +
#294500000
1!
1$
1)
#295000000
0!
0$
0)
b110 +
#295500000
1!
1$
1)
#296000000
0!
0$
0)
b111 +
#296500000
1!
1$
1)
#297000000
0!
0$
0)
b1000 +
#297500000
1!
1$
1)
#298000000
0!
0$
0)
b1001 +
#298500000
1!
1$
1)
#299000000
0!
0$
0)
b1010 +
#299500000
1!
1$
1)
#300000000
0!
b1011 #
0$
b1011 &
b011 '
0(
0)
0*
b1 +
0,
0/
10
11
14
#300500000
1!
1$
1)
#301000000
0!
0$
0)
b10 +
#301500000
1!
1$
1)
#302000000
0!
0$
0)
b11 +
#302500000
1!
1$
1)
#303000000
0!
0$
0)
b100 +
#303500000
1!
1$
1)
#304000000
0!
0$
0)
b101 +
#304500000
1!
1$
1)
#305000000
0!
0$
0)
b110 +
#305500000
1!
1$
1)
#306000000
0!
0$
0)
b111 +
#306500000
1!
1$
1)
#307000000
0!
0$
0)
b1000 +
#307500000
1!
1$
1)
#308000000
0!
0$
0)
b1001 +
#308500000
1!
1$
1)
#309000000
0!
0$
0)
b1010 +
#309500000
1!
1$
1)
#310000000
0!
0$
1(
0)
1*
b1 +
1,
1/
#310500000
1!
1$
1)
#311000000
0!
0$
0)
b10 +
#311500000
1!
1$
1)
#312000000
0!
0$
0)
b11 +
#312500000
1!
1$
1)
#313000000
0!
0$
0)
b100 +
#313500000
1!
1$
1)
#314000000
0!
0$
0)
b101 +
#314500000
1!
1$
1)
#315000000
0!
0$
0)
b110 +
#315500000
1!
1$
1)
#316000000
0!
0$
0)
b111 +
#316500000
1!
1$
1)
#317000000
0!
0$
0)
b1000 +
#317500000
1!
1$
1)
#318000000
0!
0$
0)
b1001 +
#318500000
1!
1$
1)
#319000000
0!
0$
0)
b1010 +
#319500000
1!
1$
1)
#320000000
0!
b1100 #
0$
b1100 &
b100 '
0(
0)
0*
b1 +
0,
0/
00
01
04
05
06
09
1:
1;
1>
#320500000
1!
1$
1)
#321000000
0!
0$
0)
b10 +
#321500000
1!
1$
1)
#322000000
0!
0$
0)
b11 +
#322500000
1!
1$
1)
#323000000
0!
0$
0)
b100 +
#323500000
1!
1$
1)
#324000000
0!
0$
0)
b101 +
#324500000
1!
1$
1)
#325000000
0!
0$
0)
b110 +
#325500000
1!
1$
1)
#326000000
0!
0$
0)
b111 +
#326500000
1!
1$
1)
#327000000
0!
0$
0)
b1000 +
#327500000
1!
1$
1)
#328000000
0!
0$
0)
b1001 +
#328500000
1!
1$
1)
#329000000
0!
0$
0)
b1010 +
#329500000
1!
1$
1)
#330000000
0!
0$
1(
0)
1*
b1 +
1,
1/
#330500000
1!
1$
1)
#331000000
0!
0$
0)
b10 +
#331500000
1!
1$
1)
#332000000
0!
0$
0)
b11 +
#332500000
1!
1$
1)
#333000000
0!
0$
0)
b100 +
#333500000
1!
1$
1)
#334000000
0!
0$
0)
b101 +
#334500000
1!
1$
1)
#335000000
0!
0$
0)
b110 +
#335500000
1!
1$
1)
#336000000
0!
0$
0)
b111 +
#336500000
1!
1$
1)
#337000000
0!
0$
0)
b1000 +
#337500000
1!
1$
1)
#338000000
0!
0$
0)
b1001 +
#338500000
1!
1$
1)
#339000000
0!
0$
0)
b1010 +
#339500000
1!
1$
1)
#340000000
0!
b1101 #
0$
b1101 &
b101 '
0(
0)
0*
b1 +
0,
0/
10
11
14
#340500000
1!
1$
1)
#341000000
0!
0$
0)
b10 +
#341500000
1!
1$
1)
#342000000
0!
0$
0)
b11 +
#342500000
1!
1$
1)
#343000000
0!
0$
0)
b100 +
#343500000
1!
1$
1)
#344000000
0!
0$
0)
b101 +
#344500000
1!
1$
1)
#345000000
0!
0$
0)
b110 +
#345500000
1!
1$
1)
#346000000
0!
0$
0)
b111 +
#346500000
1!
1$
1)
#347000000
0!
0$
0)
b1000 +
#347500000
1!
1$
1)
#348000000
0!
0$
0)
b1001 +
#348500000
1!
1$
1)
#349000000
0!
0$
0)
b1010 +
#349500000
1!
1$
1)
