Lab 10/temp/CPU8BIT2.vhd

-- LIBRARY ieee;
-- USE ieee.std_logic_1164.ALL;
-- USE ieee.numeric_std.ALL;

-- ENTITY CPU8BIT2 IS
--     PORT (
--         data : INOUT STD_LOGIC_VECTOR(7 DOWNTO 0);
--         adress : OUT STD_LOGIC_VECTOR(5 DOWNTO 0);
--         oe : OUT STD_LOGIC;
--         we : OUT STD_LOGIC; -- Asynchronous memory interface
--         rst : IN STD_LOGIC;
--         clk : IN STD_LOGIC
--     );
-- END;

-- ARCHITECTURE CPU_ARCH OF CPU8BIT2 IS
--     SIGNAL akku : STD_LOGIC_VECTOR(8 DOWNTO 0); -- akku(8) is carry !
--     SIGNAL adreg : STD_LOGIC_VECTOR(5 DOWNTO 0);
--     SIGNAL pc : STD_LOGIC_VECTOR(5 DOWNTO 0);
--     SIGNAL states : STD_LOGIC_VECTOR(2 DOWNTO 0);
-- BEGIN
--     PROCESS (clk, rst)
--     BEGIN
--         IF (rst = '0') THEN
--             adreg <= (OTHERS => '0'); -- start execution at memory location 0
--             states <= "000";
--             akku <= (OTHERS => '0');
--             pc <= (OTHERS => '0');
--         ELSIF rising_edge(clk) THEN
--             -- PC / Address path
--             IF (states = "000") THEN
--                 pc <= adreg + 1;
--                 adreg <= data(5 DOWNTO 0);
--             ELSE
--                 adreg <= pc;
--             END IF;
--             -- ALU / Data Path
--             CASE states IS
--                 WHEN "010" => akku <= ("0" & akku(7 DOWNTO 0)) + ("0" & data); -- add
--                 WHEN "011" => akku(7 DOWNTO 0) <= akku(7 DOWNTO 0) NOR data; -- nor
--                 WHEN "101" => akku(8) <= '0'; -- branch not taken, clear carry
--                 WHEN OTHERS => NULL; -- instr. fetch, jcc taken (000), sta (001)
--             END CASE;
--             -- State machine
--             IF (states /= "000") THEN
--                 states <= "000"; -- fetch next opcode
--             ELSIF (data(7 DOWNTO 6) = "11" AND akku(8) = '1') THEN
--                 states <= "101"; -- branch not taken
--             ELSE
--                 states <= "0" & NOT data(7 DOWNTO 6); -- execute instruction
--             END IF;
--         END IF;
--     END PROCESS;
--     -- output
--     adress <= adreg;
--     data <= "ZZZZZZZZ" WHEN states /= "001" ELSE
--         akku(7 DOWNTO 0);
--     oe <= '1' WHEN (clk = '1' OR states = "001" OR rst = '0' OR states = "101") ELSE
--         '0';
--     -- no memory access during reset and state "101" (branch not taken)
--     we <= '1' WHEN (clk = '1' OR states /= "001" OR rst = '0') ELSE
--         '0';
-- END CPU_ARCH;



-- Minimal 8 Bit CPU
LIBRARY ieee;
USE ieee.std_logic_1164.ALL;
USE ieee.numeric_std.ALL;
ENTITY CPU8BIT2 IS
    PORT (
        data_in : IN STD_LOGIC_VECTOR(7 DOWNTO 0);
        data_out : OUT STD_LOGIC_VECTOR(7 DOWNTO 0);
        adress : OUT STD_LOGIC_VECTOR(5 DOWNTO 0);
        oe : OUT STD_LOGIC;
        we : OUT STD_LOGIC; -- Asynchronous memory interface
        rst : IN STD_LOGIC;
        clk : IN STD_LOGIC);
END;
ARCHITECTURE CPU_ARCH OF CPU8BIT2 IS
    SIGNAL akku : STD_LOGIC_VECTOR(8 DOWNTO 0); -- akku(8) is carry !
    SIGNAL adreg : unsigned(5 DOWNTO 0);
    SIGNAL pc : unsigned(5 DOWNTO 0);
    SIGNAL states : STD_LOGIC_VECTOR(2 DOWNTO 0);
BEGIN
    PROCESS (clk, rst)
    BEGIN
        IF (rst = '0') THEN
            adreg <= (OTHERS => '0'); -- start execution at memory location 0
            states <= "000";
            akku <= (OTHERS => '0');
            pc <= (OTHERS => '0');
        ELSIF rising_edge(clk) THEN
            -- PC / Adress path
            IF (states = "000") THEN
                pc <= adreg + 1;
                adreg <= unsigned(data_in(5 DOWNTO 0));
            ELSE
                adreg <= pc;
            END IF;
            -- ALU / Data Path
            CASE states IS
                WHEN "010" => akku <= STD_LOGIC_VECTOR(unsigned(("0" & akku(7 DOWNTO 0))) + unsigned("0" & data_in)); -- add
                WHEN "011" => akku(7 DOWNTO 0) <= akku(7 DOWNTO 0) NOR data_in; -- nor
                WHEN "101" => akku(8) <= '0'; -- branch not taken, clear carry
                WHEN OTHERS => NULL; -- instr. fetch, jcc taken (000), sta (001)
            END CASE;
            -- State machine
            IF (states /= "000") THEN
                states <= "000"; -- fetch next opcode
            ELSIF (data_in(7 DOWNTO 6) = "11" AND akku(8) = '1') THEN
                states <= "101"; -- branch not taken
            ELSE
                states <= "0" & NOT data_in(7 DOWNTO 6); -- execute instruction
            END IF;
        END IF;
    END PROCESS;
    -- output
    adress <= STD_LOGIC_VECTOR(adreg);
    data_out <= "ZZZZZZZZ" WHEN states /= "001" ELSE
        akku(7 DOWNTO 0);
    oe <= '1' WHEN (clk = '1' OR states = "001" OR rst = '0' OR states = "101") ELSE
        '0';
    -- no memory access during reset and state "101" (branch not taken)
    we <= '1' WHEN (clk = '1' OR states /= "001" OR rst = '0') ELSE
        '0';
END CPU_ARCH;

Lab 10/temp/CPU8BIT2_tb.vhd
LIBRARY ieee;
USE ieee.std_logic_1164.ALL;
USE ieee.numeric_std.ALL;

ENTITY CPU8BIT2_TB IS
END CPU8BIT2_TB;

ARCHITECTURE behavior OF CPU8BIT2_TB IS

    -- Component Declaration for the Unit Under Test (UUT)
    COMPONENT CPU8BIT2
        PORT (
            data_in : IN STD_LOGIC_VECTOR(7 DOWNTO 0);
            data_out : OUT STD_LOGIC_VECTOR(7 DOWNTO 0);
            adress : OUT STD_LOGIC_VECTOR(5 DOWNTO 0);
            oe : OUT STD_LOGIC;
            we : OUT STD_LOGIC;
            rst : IN STD_LOGIC;
            clk : IN STD_LOGIC
        );
    END COMPONENT;

    --Inputs
    SIGNAL data_in : STD_LOGIC_VECTOR(7 DOWNTO 0) := (OTHERS => '0');
    SIGNAL rst : STD_LOGIC := '0';
    SIGNAL clk : STD_LOGIC := '0';

    --Outputs
    SIGNAL data_out : STD_LOGIC_VECTOR(7 DOWNTO 0);
    SIGNAL adress : STD_LOGIC_VECTOR(5 DOWNTO 0);
    SIGNAL oe : STD_LOGIC;
    SIGNAL we : STD_LOGIC;

    -- Clock period definitions
    SIGNAL finished : STD_LOGIC := '0';
    CONSTANT clk_period : TIME := 10 ns;

BEGIN

    -- Instantiate the Unit Under Test (UUT)
    uut : CPU8BIT2 PORT MAP(
        data_in => data_in,
        data_out => data_out,
        adress => adress,
        oe => oe,
        we => we,
        rst => rst,
        clk => clk
    );

    -- Clock process definitions
    clk_process : PROCESS
    BEGIN
        clk <= '0';
        WAIT FOR clk_period/2;
        clk <= '1';
        WAIT FOR clk_period/2;
        IF (finished = '1') THEN
            WAIT;
        END IF;
    END PROCESS;

    -- Stimulus process
    stim_proc : PROCESS
    BEGIN
        -- hold reset state for 100 ns.
        WAIT FOR 40 ns;
        rst <= '1';
        
        WAIT FOR clk_period * 10;

        -- Apply stimulus here
        -- Example: Change data_in and check data_out, adress, etc.

        -- Finish the simulation
        finished <= '1';
        WAIT;
    END PROCESS;

END;

Lab 10/temp/out.vcd
$date
  Mon May 27 14:22:08 2024
$end
$version
  GHDL v0
$end
$timescale
  1 fs
$end
$scope module standard $end
$upscope $end
$scope module std_logic_1164 $end
$upscope $end
$scope module numeric_std $end
$upscope $end
$scope module cpu8bit2_tb $end
$var reg 8 ! data_in[7:0] $end
$var reg 1 " rst $end
$var reg 1 # clk $end
$var reg 8 $ data_out[7:0] $end
$var reg 6 % adress[5:0] $end
$var reg 1 & oe $end
$var reg 1 ' we $end
$var reg 1 ( finished $end
$scope module uut $end
$var reg 8 ) data_in[7:0] $end
$var reg 8 * data_out[7:0] $end
$var reg 6 + adress[5:0] $end
$var reg 1 , oe $end
$var reg 1 - we $end
$var reg 1 . rst $end
$var reg 1 / clk $end
$var reg 9 0 akku[8:0] $end
$var reg 6 1 adreg[5:0] $end
$var reg 6 2 pc[5:0] $end
$var reg 3 3 states[2:0] $end
$upscope $end
$upscope $end
$enddefinitions $end
#0
b00000000 !
0"
0#
bZZZZZZZZ $
b000000 %
1&
1'
0(
b00000000 )
bZZZZZZZZ *
b000000 +
1,
1-
0.
0/
b000000000 0
b000000 1
b000000 2
b000 3
#5000000
1#
1/
#10000000
0#
0/
#15000000
1#
1/
#20000000
0#
0/
#25000000
1#
1/
#30000000
0#
0/
#35000000
1#
1/
#40000000
1"
0#
0&
0,
1.
0/
#45000000
1#
1&
1,
1/
b000001 2
b011 3
#50000000
0#
0&
0,
0/
#55000000
1#
b000001 %
1&
b000001 +
1,
1/
b011111111 0
b000001 1
b000 3
#60000000
0#
0&
0,
0/
#65000000
1#
b000000 %
1&
b000000 +
1,
1/
b000000 1
b000010 2
b011 3
#70000000
0#
0&
0,
0/
#75000000
1#
b000010 %
1&
b000010 +
1,
1/
b000000000 0
b000010 1
b000 3
#80000000
0#
0&
0,
0/
#85000000
1#
b000000 %
1&
b000000 +
1,
1/
b000000 1
b000011 2
b011 3
#90000000
0#
0&
0,
0/
#95000000
1#
b000011 %
1&
b000011 +
1,
1/
b011111111 0
b000011 1
b000 3
#100000000
0#
0&
0,
0/
#105000000
1#
b000000 %
1&
b000000 +
1,
1/
b000000 1
b000100 2
b011 3
#110000000
0#
0&
0,
0/
#115000000
1#
b000100 %
1&
b000100 +
1,
1/
b000000000 0
b000100 1
b000 3
#120000000
0#
0&
0,
0/
#125000000
1#
b000000 %
1&
b000000 +
1,
1/
b000000 1
b000101 2
b011 3
#130000000
0#
0&
0,
0/
#135000000
1#
b000101 %
1&
b000101 +
1,
1/
b011111111 0
b000101 1
b000 3
#140000000
0#
0&
1(
0,
0/
#145000000
1#
b000000 %
1&
b000000 +
1,
1/
b000000 1
b000110 2
b011 3
