Lab 6/ShiftRegister8B/ShiftRegister8B.vhd
library IEEE;
use IEEE.STD_LOGIC_1164.ALL;
use IEEE.NUMERIC_STD.ALL; -- Uncommented and added

entity ShiftRegister8B is
    port(
        clock : in std_logic;
        reset : in std_logic;
        cmd : in std_logic_vector(2 downto 0);
        datain : in std_logic_vector(7 downto 0);
        dataout : out std_logic_vector(7 downto 0));
end ShiftRegister8B;

architecture Behavioral of ShiftRegister8B is

signal temp : std_logic_vector(7 downto 0);
signal tempin : std_logic_vector(7 downto 0);
signal temp_unsigned : unsigned(7 downto 0); -- Added signal for unsigned conversion

begin 
    
    tempin <= datain;
    synchronous_process : process (clock, reset)

    begin

	if falling_edge (reset) then
		temp <= "00000000";
	else
        if rising_edge (clock) then
            case cmd is 
        when "001" => --Sets all bits to 1
            temp <= "11111111";
        when "010" => --Reset synchronus to 0
            temp <= "00000000";
        when "111" => --Load datain to dataout
            temp <= tempin;
        when "011" => --Shift Right 
            temp(6 downto 0) <= temp(7 downto 1) ;
            temp(7) <= '0';
        when "100" => --Shift Left
            temp(7 downto 1) <= temp(6 downto 0) ;
            temp(0) <= '0';
        when "101" => --Count Up
        
            temp_unsigned <= unsigned(temp); -- Convert to unsigned
            temp_unsigned <= temp_unsigned + 1; -- Perform arithmetic operation
            temp <= std_logic_vector(temp_unsigned); -- Convert back to std_logic_vector
        
            when others => --Count Down
            
            temp_unsigned <= unsigned(temp); -- Convert to unsigned
            temp_unsigned <= temp_unsigned - 1; -- Perform arithmetic operation
            temp <= std_logic_vector(temp_unsigned); -- Convert back to std_logic_vector
        
        end case;
	end if;
    end if;
end process;

dataout <= temp;
end Behavioral;

Lab 6/ShiftRegister8B/ShiftRegister8B_tb.vhd

LIBRARY ieee;
USE ieee.std_logic_1164.ALL;

ENTITY ShiftRegister8B_tb IS
END ShiftRegister8B_tb;
 
ARCHITECTURE behavior OF ShiftRegister8B_tb IS 

    COMPONENT ShiftRegister8B
    PORT(
         clock : IN  std_logic;
         reset : IN  std_logic;
         cmd : IN  std_logic_vector(2 downto 0);
         datain : IN  std_logic_vector(7 downto 0);
         dataout : OUT  std_logic_vector(7 downto 0)
        );
    END COMPONENT;
    

   --Inputs
   signal clock : std_logic := '0';
   signal reset : std_logic := '0';
   signal cmd : std_logic_vector(2 downto 0) := (others => '0');
   signal datain : std_logic_vector(7 downto 0) := (others => '0');

 	--Outputs
   signal dataout : std_logic_vector(7 downto 0);

   -- Clock period definitions
   constant clock_period : time := 10 ns;
 
BEGIN
 
	-- Instantiate the Unit Under Test (UUT)
   uut: ShiftRegister8B PORT MAP (
          clock => clock,
          reset => reset,
          cmd => cmd,
          datain => datain,
          dataout => dataout
        );

   -- Clock process definitions
   clock_process :process
   begin
		clock <= '0';
		wait for clock_period/2;
		clock <= '1';
		wait for clock_period/2;
   end process;
 

   -- Stimulus process
   stim_proc: process
   begin		

        reset <= '1';
        --dataout<= "00000000";
      -- hold reset state for 100 ns.
      wait for 10 ns;

        reset <= '0';
		
		cmd <= "111"; --loads the datain to dataout
		datain <= "11010101";
		
		wait for 20 ns;
		
		cmd <= "001"; --set all the bits to 1
		
		wait for 20 ns;
		
		cmd <= "010"; --reset all bits to 0
		
		wait for 20 ns;
		
		
		cmd <= "111"; --loads the datain to dataout
		datain <= "11011011";

        wait for 20 ns;

        --!
        cmd <= "101";

        wait for 40 ns;

        cmd <= "011";

        wait for 40 ns;

        cmd <= "100";
		
      wait for clock_period*10;

      -- insert stimulus here 

      wait;
   end process;

END;

Lab 06/ShiftRegister8B/out.vcd
$date
  Sun Apr 21 22:44:14 2024
$end
$version
  GHDL v0
$end
$timescale
  1 fs
$end
$scope module standard $end
$upscope $end
$scope module std_logic_1164 $end
$upscope $end
$scope module numeric_std $end
$upscope $end
$scope module shiftregister8b_tb $end
$var reg 1 ! clock $end
$var reg 1 " reset $end
$var reg 3 # cmd[2:0] $end
$var reg 8 $ datain[7:0] $end
$var reg 8 % dataout[7:0] $end
$scope module uut $end
$var reg 1 & clock $end
$var reg 1 ' reset $end
$var reg 3 ( cmd[2:0] $end
$var reg 8 ) datain[7:0] $end
$var reg 8 * dataout[7:0] $end
$var reg 8 + temp[7:0] $end
$var reg 8 , tempin[7:0] $end
$var reg 8 - temp_unsigned[7:0] $end
$upscope $end
$upscope $end
$enddefinitions $end
#0
0!
1"
b000 #
b00000000 $
bUUUUUUUU %
0&
1'
b000 (
b00000000 )
bUUUUUUUU *
bUUUUUUUU +
b00000000 ,
bUUUUUUUU -
#5000000
1!
1&
bXXXXXXXX -
#10000000
0!
0"
b111 #
b11010101 $
b00000000 %
0&
0'
b111 (
b11010101 )
b00000000 *
b00000000 +
b11010101 ,
#15000000
1!
b11010101 %
1&
b11010101 *
b11010101 +
#20000000
0!
0&
#25000000
1!
1&
#30000000
0!
b001 #
0&
b001 (
#35000000
1!
b11111111 %
1&
b11111111 *
b11111111 +
#40000000
0!
0&
#45000000
1!
1&
#50000000
0!
b010 #
0&
b010 (
#55000000
1!
b00000000 %
1&
b00000000 *
b00000000 +
#60000000
0!
0&
#65000000
1!
1&
#70000000
0!
b111 #
b11011011 $
0&
b111 (
b11011011 )
b11011011 ,
#75000000
1!
b11011011 %
1&
b11011011 *
b11011011 +
#80000000
0!
0&
#85000000
1!
1&
#90000000
0!
b101 #
0&
b101 (
#95000000
1!
bXXXXXXXX %
1&
bXXXXXXXX *
bXXXXXXXX +
#100000000
0!
0&
#105000000
1!
1&
#110000000
0!
0&
#115000000
1!
1&
#120000000
0!
0&
#125000000
1!
1&
#130000000
0!
b011 #
0&
b011 (
#135000000
1!
b0XXXXXXX %
1&
b0XXXXXXX *
b0XXXXXXX +
#140000000
0!
0&
#145000000
1!
b00XXXXXX %
1&
b00XXXXXX *
b00XXXXXX +
#150000000
0!
0&
#155000000
1!
b000XXXXX %
1&
b000XXXXX *
b000XXXXX +
#160000000
0!
0&
#165000000
1!
b0000XXXX %
1&
b0000XXXX *
b0000XXXX +
#170000000
0!
b100 #
0&
b100 (
#175000000
1!
b000XXXX0 %
1&
b000XXXX0 *
b000XXXX0 +
#180000000
0!
0&
#185000000
1!
b00XXXX00 %
1&
b00XXXX00 *
b00XXXX00 +
#190000000
0!
0&
#195000000
1!
b0XXXX000 %
1&
b0XXXX000 *
b0XXXX000 +
#200000000
0!
0&
#205000000
1!
bXXXX0000 %
1&
bXXXX0000 *
bXXXX0000 +
#210000000
0!
0&
#215000000
1!
bXXX00000 %
1&
bXXX00000 *
bXXX00000 +
#220000000
0!
0&
#225000000
1!
bXX000000 %
1&
bXX000000 *
bXX000000 +
#230000000
0!
0&
#235000000
1!
bX0000000 %
1&
bX0000000 *
bX0000000 +
#240000000
0!
0&
#245000000
1!
b00000000 %
1&
b00000000 *
b00000000 +
