Lab 03/SeqDetector1101/SeqDetector1101.vhd

library IEEE;
use IEEE.STD_LOGIC_1164.ALL;

entity SeqDetector1101 is
    Port ( data : in  STD_LOGIC;
           clk : in  STD_LOGIC;
           VALID : out  STD_LOGIC
			);
end SeqDetector1101;

architecture Behavioral of SeqDetector1101 is

type state_t is(initial, got1, got11, got110);
signal state : state_t := initial;
signal output_tmp : std_logic;
begin

	process(clk)begin
		if(clk = '0' and clk'Event) then
		case state is
			when initial =>
				if(data = '0') then
					state <= initial;
					output_tmp <= '0';
				elsif(data = '1') then
					state <= got1;
					output_tmp <= '0';
				end if;
			when got1 =>
				if(data = '0') then
					state <= initial;
					output_tmp <= '0';
				elsif(data = '1') then
					state <= got11;
					output_tmp <= '0';
				end if;
			when got11 =>
				if(data = '0') then
					state <= got110;
					output_tmp <= '0';
				elsif(data = '1') then
					state <= got11;
					output_tmp <= '0';
				end if;
			when got110 =>
				if(data = '0') then
					state <= initial;
					output_tmp <= '0';
				elsif(data = '1') then
					state <= got1;
					output_tmp <= '1';
				end if;
		end case;
		end if;
	end process;
	
	VALID <= output_tmp;

end Behavioral;

Lab 3/SeqDetector1101/SeqDetector1101_tb.vhd
LIBRARY ieee;
USE ieee.std_logic_1164.ALL;

ENTITY SeqDetector1101_tb IS
END SeqDetector1101_tb;
 
ARCHITECTURE behavior OF SeqDetector1101_tb IS 
 
    COMPONENT SeqDetector1101
    PORT(
         data : IN  std_logic;
         clk : IN  std_logic;
         VALID : OUT  std_logic
         --clk_out : out STD_LOGIC
        );
    END COMPONENT;
    

   --Inputs
   signal data : std_logic := '0';
   signal clk : std_logic := '0';

 	--Outputs
   signal VALID : std_logic;
   --signal clk_out :std_logic;

   -- Clock period definitions
   constant clk_period : time := 10 ns;
 
BEGIN
 
	-- Instantiate the Unit Under Test (UUT)
   uut: SeqDetector1101 PORT MAP (
          data => data,
          clk => clk,
          VALID => VALID
         --clk_out => clk_out
        );

   -- Clock process definitions
   clk_process :process
   begin
		clk <= '0';
		wait for clk_period/2;
		clk <= '1';
		wait for clk_period/2;
   end process;
 

   -- Stimulus process
   stim_proc: process
   begin		
      -- hold reset state for 100 ns.
      wait for 100 ns;	

      wait for clk_period*10;

      -- insert stimulus here 
		
		data <= '0';
		wait for 10 ns;
		
		data <= '1';
		wait for 10 ns;
		
		data <= '1';
		wait for 10 ns;
		
		data <= '0';
		wait for 10 ns;
		
		data <= '1';
		wait for 10 ns;
		
		data <= '1';
		wait for 10 ns;
		
		data <= '0';
		wait for 10 ns;
		
		data <= '1';
		wait for 10 ns;

      wait;
   end process;

END;

Lab 03/SeqDetector1101/out.vcd
$date
  Mon Mar 11 16:59:40 2024
$end
$version
  GHDL v0
$end
$timescale
  1 fs
$end
$scope module standard $end
$upscope $end
$scope module std_logic_1164 $end
$upscope $end
$scope module seqdetector1101_tb $end
$var reg 1 ! data $end
$var reg 1 " clk $end
$var reg 1 # valid $end
$scope module uut $end
$var reg 1 $ data $end
$var reg 1 % clk $end
$var reg 1 & valid $end
$comment state is not handled $end
$var reg 1 ' output_tmp $end
$upscope $end
$upscope $end
$enddefinitions $end
#0
0!
0"
U#
0$
0%
U&
U'
#5000000
1"
1%
#10000000
0"
0#
0%
0&
0'
#15000000
1"
1%
#20000000
0"
0%
#25000000
1"
1%
#30000000
0"
0%
#35000000
1"
1%
#40000000
0"
0%
#45000000
1"
1%
#50000000
0"
0%
#55000000
1"
1%
#60000000
0"
0%
#65000000
1"
1%
#70000000
0"
0%
#75000000
1"
1%
#80000000
0"
0%
#85000000
1"
1%
#90000000
0"
0%
#95000000
1"
1%
#100000000
0"
0%
#105000000
1"
1%
#110000000
0"
0%
#115000000
1"
1%
#120000000
0"
0%
#125000000
1"
1%
#130000000
0"
0%
#135000000
1"
1%
#140000000
0"
0%
#145000000
1"
1%
#150000000
0"
0%
#155000000
1"
1%
#160000000
0"
0%
#165000000
1"
1%
#170000000
0"
0%
#175000000
1"
1%
#180000000
0"
0%
#185000000
1"
1%
#190000000
0"
0%
#195000000
1"
1%
#200000000
0"
0%
#205000000
1"
1%
#210000000
1!
0"
1$
0%
#215000000
1"
1%
#220000000
0"
0%
#225000000
1"
1%
#230000000
0!
0"
0$
0%
#235000000
1"
1%
#240000000
1!
0"
1#
1$
0%
1&
1'
#245000000
1"
1%
#250000000
0"
0#
0%
0&
0'
#255000000
1"
1%
#260000000
0!
0"
0$
0%
#265000000
1"
1%
#270000000
1!
0"
1#
1$
0%
1&
1'
#275000000
1"
1%
#280000000
0"
0#
0%
0&
0'
