Lab 07/ROM/ROM.vhd
library IEEE;
use IEEE.STD_LOGIC_1164.ALL;
use ieee.numeric_std.all;

entity ROM is
    Port ( RD : in  STD_LOGIC;
           Addr : in  STD_LOGIC_VECTOR(3 downto 0);
           Reset : in  STD_LOGIC;
           Data_out : out  STD_LOGIC_VECTOR(7 downto 0);
			  CLK : in STD_LOGIC);
end ROM;

architecture Behavioral of ROM is

type ROM_TYPE is array(0 to 15) of std_logic_vector(7 downto 0);
signal Data : ROM_TYPE;

begin

	process(CLK) begin
		if(CLK = '1' and CLK'event) then
		if(Reset = '0') then
			for item in 0 to 15 loop
				Data(item) <= STD_LOGIC_VECTOR(to_unsigned(item,8));
			end loop;
		elsif(RD = '1') then
			Data_out <= Data(to_integer(unsigned(Addr)));
		end if;
		end if;
	end process;

end Behavioral;

Lab 7/ROM/ROM_tb.vhd
LIBRARY ieee;
USE ieee.std_logic_1164.ALL;

ENTITY ROM_tb IS
END ROM_tb;
 
ARCHITECTURE behavior OF ROM_tb IS 

    COMPONENT ROM
    PORT(
         RD : IN  std_logic;
         Addr : IN  std_logic_vector(3 downto 0);
         Reset : IN  std_logic;
         Data_out : OUT  std_logic_vector(7 downto 0);
         CLK : IN  std_logic
        );
    END COMPONENT;
  
   --Inputs
   signal RD : std_logic := '0';
   signal Addr : std_logic_vector(3 downto 0) := (others => '0');
   signal Reset : std_logic := '0';
   signal CLK : std_logic := '0';

 	--Outputs
   signal Data_out : std_logic_vector(7 downto 0);

   constant CLK_period : time := 10 ns;
 
BEGIN
   uut: ROM PORT MAP (
          RD => RD,
          Addr => Addr,
          Reset => Reset,
          Data_out => Data_out,
          CLK => CLK
        );
   CLK_process :process
   begin
		CLK <= '0';
		wait for CLK_period/2;
		CLK <= '1';
		wait for CLK_period/2;
   end process;

   stim_proc: process
   begin
      wait for 100 ns;	
		
		Reset <= '1';
		wait for 20 ns;
		Reset <= '0';
		wait for 20 ns;
		Reset <= '1';
		wait for 20 ns;
		
		RD <= '1';
		Addr <= "1100";
		
		wait for 20 ns;
		Addr <= "0010";

      wait for CLK_period*10;

      wait;
   end process;
END;

Lab 7/ROM/out.vcd
$date
  Mon May 06 10:42:27 2024
$end
$version
  GHDL v0
$end
$timescale
  1 fs
$end
$scope module standard $end
$upscope $end
$scope module std_logic_1164 $end
$upscope $end
$scope module numeric_std $end
$upscope $end
$scope module rom_tb $end
$var reg 1 ! rd $end
$var reg 4 " addr[3:0] $end
$var reg 1 # reset $end
$var reg 1 $ clk $end
$var reg 8 % data_out[7:0] $end
$scope module uut $end
$var reg 1 & rd $end
$var reg 4 ' addr[3:0] $end
$var reg 1 ( reset $end
$var reg 8 ) data_out[7:0] $end
$var reg 1 * clk $end
$comment data is not handled $end
$upscope $end
$upscope $end
$enddefinitions $end
#0
0!
b0000 "
0#
0$
bUUUUUUUU %
0&
b0000 '
0(
bUUUUUUUU )
0*
#5000000
1$
1*
#10000000
0$
0*
#15000000
1$
1*
#20000000
0$
0*
#25000000
1$
1*
#30000000
0$
0*
#35000000
1$
1*
#40000000
0$
0*
#45000000
1$
1*
#50000000
0$
0*
#55000000
1$
1*
#60000000
0$
0*
#65000000
1$
1*
#70000000
0$
0*
#75000000
1$
1*
#80000000
0$
0*
#85000000
1$
1*
#90000000
0$
0*
#95000000
1$
1*
#100000000
1#
0$
1(
0*
#105000000
1$
1*
#110000000
0$
0*
#115000000
1$
1*
#120000000
0#
0$
0(
0*
#125000000
1$
1*
#130000000
0$
0*
#135000000
1$
1*
#140000000
1#
0$
1(
0*
#145000000
1$
1*
#150000000
0$
0*
#155000000
1$
1*
#160000000
1!
b1100 "
0$
1&
b1100 '
0*
#165000000
1$
b00001100 %
b00001100 )
1*
#170000000
0$
0*
#175000000
1$
1*
#180000000
b0010 "
0$
b0010 '
0*
#185000000
1$
b00000010 %
b00000010 )
1*
