Lab 8/Divider.vhd
library ieee;
use ieee.std_logic_1164.all;
use ieee.numeric_std.all;

entity Divider is
    port (
         a : in std_logic_vector(7 downto 0);
         b : in std_logic_vector(3 downto 0);
         Wrong : out std_logic := '0';
         remainder : out std_logic_vector(3 downto 0);
         quotient : out std_logic_vector(3 downto 0);
         reset : in std_logic
    );
end Divider;

architecture behavior of Divider is

begin 
    process(a, b, reset)

    variable quotienttmp : unsigned(7 downto 0);
    variable remaindertmp : unsigned(7 downto 0);
   
    begin
        if reset = '1' then 
            remainder <= (others => '0');
            quotient <= (others => '0');
            Wrong <= '0';
        else 
            Wrong <= '0';
            if b = "0000" and a /= "0000" then -- if b = 0 its wrong (divide by zero)
                Wrong <= '1';
            elsif unsigned(a(7 downto 4)) >= unsigned(b) then -- tazmin mishavad quotient 4 bit ast
                Wrong <= '1';
            else
                quotienttmp := (others => '0');
                remaindertmp := (others => '0');
            
                for i in 7 downto 0 loop

                    remaindertmp(6 downto 1) := remaindertmp(5 downto 0);
                    remaindertmp(0) := a(i);
                    
                    if remaindertmp >= unsigned(b) then
                        remaindertmp := remaindertmp - unsigned(b);
                        quotienttmp(i) := '1';
                    end if;
                end loop;
                
                remainder <= std_logic_vector(remaindertmp(3 downto 0));
                quotient <= std_logic_vector(quotienttmp(3 downto 0));
            end if;
        end if;
    end process;

end behavior;

Lab 08/Divider_tb.vhd
LIBRARY ieee;
USE ieee.std_logic_1164.ALL;

ENTITY Divider_tb IS
END Divider_tb;

ARCHITECTURE behavior OF Divider_tb IS

    COMPONENT Divider
    port (
        a : in std_logic_vector(7 downto 0);
        b : in std_logic_vector(3 downto 0);
        Wrong : out std_logic;
        remainder : out std_logic_vector(3 downto 0);
        quotient : out std_logic_vector(3 downto 0);
        reset : in std_logic
    );
    END COMPONENT;

--Inputs
    SIGNAL a : STD_LOGIC_VECTOR (7 DOWNTO 0) := (OTHERS => '0');
    SIGNAL b : STD_LOGIC_VECTOR (3 DOWNTO 0) := (OTHERS => '0');
    signal reset :std_logic := '0';
--Outputs
    SIGNAL Wrong : STD_LOGIC := '0';
    SIGNAL remainder : STD_LOGIC_VECTOR (3 DOWNTO 0) := (OTHERS => '0');
    SIGNAL quotient : STD_LOGIC_VECTOR (3 DOWNTO 0) := (OTHERS => '0');


BEGIN
    uut : Divider PORT MAP(
            a => a,
            b => b,
            Wrong => Wrong,
            remainder => remainder,
            quotient => quotient,
            reset => reset
        );


        stim_proc :PROCESS
        BEGIN
            reset <= '1';

            wait for 10 ns;

            reset <= '0';

            a <= "00000001"; -- 1
            b <= "0001";     -- 1
            -- Expected quotient: 1, remainder: 0
            wait for 20 ns;

            a <= "10000000"; -- 128
            b <= "0010";     -- 2
            -- Expected quotient: 64, remainder: 0 --error
            wait for 20 ns;

            a <= "00010000"; --16
            b <= "0010";      --2
            -- Expected quotient: 8, remainder: 0 

            wait for 20 ns;

            a <= "00000000"; --0
            b <= "0010";      --2
            -- Expected quotient: 0, remainder: 0

            wait for 20 ns;

            a <= "00001001"; -- 9
            b <= "0100";     -- 4
            -- Expected quotient: 2, remainder: 1
            wait for 20 ns;

            a <= "00100000"; --32
            b <= "0101";     -- 5
            -- Expected quotient: 6, remainder: 2
            wait for 20 ns;

            a <= "11110000"; -- 240
            b <= "0110";     -- 6
            -- Expected quotient: 40, remainder: 0 -error
            wait for 20 ns;

            a <= "01010101"; -- 85
            b <= "1000";     -- 8
            -- Expected quotient: 10, remainder: 5
            wait for 20 ns;

            a <= "00001111"; -- 15
            b <= "1001";     -- 9
            -- Expected quotient: 1, remainder: 6
            wait for 20 ns;

            a <= "01000110"; --70
            b <= "1010";     -- 10
            -- Expected quotient: 7, remainder: 0
            wait for 20 ns;

            WAIT;
        END PROCESS;
    END;

Lab 08/out.vcd
$date
  Sun May 12 23:45:26 2024
$end
$version
  GHDL v0
$end
$timescale
  1 fs
$end
$scope module standard $end
$upscope $end
$scope module std_logic_1164 $end
$upscope $end
$scope module numeric_std $end
$upscope $end
$scope module divider_tb $end
$var reg 8 ! a[7:0] $end
$var reg 4 " b[3:0] $end
$var reg 1 # reset $end
$var reg 1 $ wrong $end
$var reg 4 % remainder[3:0] $end
$var reg 4 & quotient[3:0] $end
$scope module uut $end
$var reg 8 ' a[7:0] $end
$var reg 4 ( b[3:0] $end
$var reg 1 ) wrong $end
$var reg 4 * remainder[3:0] $end
$var reg 4 + quotient[3:0] $end
$var reg 1 , reset $end
$upscope $end
$upscope $end
$enddefinitions $end
#0
b00000000 !
b0000 "
1#
0$
b0000 %
b0000 &
b00000000 '
b0000 (
0)
b0000 *
b0000 +
1,
#10000000
b00000001 !
b0001 "
0#
b0001 &
b00000001 '
b0001 (
b0001 +
0,
#30000000
b10000000 !
b0010 "
1$
b10000000 '
b0010 (
1)
#50000000
b00010000 !
0$
b1000 &
b00010000 '
0)
b1000 +
#70000000
b00000000 !
b0000 &
b00000000 '
b0000 +
#90000000
b00001001 !
b0100 "
b0001 %
b0010 &
b00001001 '
b0100 (
b0001 *
b0010 +
#110000000
b00100000 !
b0101 "
b0010 %
b0110 &
b00100000 '
b0101 (
b0010 *
b0110 +
#130000000
b11110000 !
b0110 "
1$
b11110000 '
b0110 (
1)
#150000000
b01010101 !
b1000 "
0$
b0101 %
b1010 &
b01010101 '
b1000 (
0)
b0101 *
b1010 +
#170000000
b00001111 !
b1001 "
b0110 %
b0001 &
b00001111 '
b1001 (
b0110 *
b0001 +
#190000000
b01000110 !
b1010 "
b0000 %
b0111 &
b01000110 '
b1010 (
b0000 *
b0111 +
