Lab 06/ShiftRegister4B/DFF.vhd

library IEEE;
use IEEE.STD_LOGIC_1164.ALL;

entity DFF is
    Port ( D : in  STD_LOGIC;
			  Load : in STD_LOGIC;
           clk : in  STD_LOGIC;
           Q : out  STD_LOGIC);
end DFF;

architecture Behavioral of DFF is

begin
	process(clk)
		begin 
			if(clk = '1' and clk'event and Load = '1') then
				Q <= D;
			end if;
	end process;


end Behavioral;

Lab 6/ShiftRegister4B/Mux4x1.vhd

library IEEE;
use IEEE.STD_LOGIC_1164.ALL;

entity Mux4x1 is
    Port ( I : in  STD_LOGIC_VECTOR(3 downto 0);
           S : in  STD_LOGIC_VECTOR(1 downto 0);
           O : out  STD_LOGIC);
end Mux4x1;

architecture Behavioral of Mux4x1 is

signal W : STD_LOGIC_VECTOR(3 downto 0);

begin

	W(0) <= I(0) and (not S(1) and (not S(0)));
	W(1) <= I(1) and (not S(1) and S(0));
	W(2) <= I(2) and (S(1) and (not S(0)));
	W(3) <= I(3) and S(1) and S(0);
	
	O <= W(0) or W(1) or W(2) or W(3);

end Behavioral;

Lab 6/ShiftRegister4B/PriorityEncoder4x2.vhd

library IEEE;
use IEEE.STD_LOGIC_1164.ALL;

entity PriorityEncoder4x2 is
    Port ( I : in  STD_LOGIC_VECTOR(3 downto 0);
           O : out  STD_LOGIC_VECTOR(1 downto 0);
			  V : OUT STD_LOGIC);
end PriorityEncoder4x2;

architecture Behavioral of PriorityEncoder4x2 is

begin

	process(I) begin
		if(I(0) = '1') then
			O <= "00";
			V <= '1';
		elsif(I(1) = '1') then
			O <= "01";
			V <= '1';
		elsif(I(2) = '1') then
			O <= "10";
			V <= '1';
		elsif(I(3) = '1') then
			O <= "11";
			V <= '1';
		else
			O <= "00";
			V <= '0';
		end if;
	end process;

end Behavioral;

Lab 06/ShiftRegister4B/ShiftRegister4B.vhd

library IEEE;
use IEEE.STD_LOGIC_1164.ALL;

entity ShiftRegister4B is
    Port ( Reset : in  STD_LOGIC;
           Load : in  STD_LOGIC;
           L : in  STD_LOGIC;
           R : in  STD_LOGIC;
           D : in  STD_LOGIC_VECTOR(3 downto 0);
           Q : out  STD_LOGIC_VECTOR(3 downto 0);
			  clk : in STD_LOGIC);
end ShiftRegister4B;

architecture Behavioral of ShiftRegister4B is

component DFF is
    Port ( D : in  STD_LOGIC;
			  Load : in STD_LOGIC;
           clk : in  STD_LOGIC;
           Q : out  STD_LOGIC);
end component;

component Mux4x1 is
    Port ( I : in  STD_LOGIC_VECTOR(3 downto 0);
           S : in  STD_LOGIC_VECTOR(1 downto 0);
           O : out  STD_LOGIC);
end component;

component PriorityEncoder4x2 is
    Port ( I : in  STD_LOGIC_VECTOR(3 downto 0);
           O : out  STD_LOGIC_VECTOR(1 downto 0);
			  V : OUT STD_LOGIC);
end component;

signal M, Q_tmp : STD_LOGIC_VECTOR(3 downto 0);
signal P : STD_LOGIC_VECTOR(1 downto 0);
signal Valid : STD_LOGIC;

begin
	
	priorityEncoder1 : PriorityEncoder4x2 Port Map(I(0) => Reset, I(1) => Load, 
																  I(2) => L, I(3) => R, O => P, V => Valid);
	
	Mux3 : Mux4x1 Port Map(I(0) => '0', I(1) => D(3), I(2) => Q_tmp(2), I(3) => '0', 
								  S => P, O => M(3));
	Mux2 : Mux4x1 Port Map(I(0) => '0', I(1) => D(2), I(2) => Q_tmp(1), I(3) => Q_tmp(3), 
								  S => P, O => M(2));
	Mux1 : Mux4x1 Port Map(I(0) => '0', I(1) => D(1), I(2) => Q_tmp(0), I(3) => Q_tmp(2), 
								  S => P, O => M(1));
	Mux0 : Mux4x1 Port Map(I(0) => '0', I(1) => D(0), I(2) => '0', I(3) => Q_tmp(1), 
								  S => P, O => M(0));
	
	Q <= Q_tmp;
	
	DFF3 : DFF Port Map(D => M(3), Load => Valid, clk => clk, Q => Q_tmp(3));
	DFF2 : DFF Port Map(D => M(2), Load => Valid, clk => clk, Q => Q_tmp(2));
	DFF1 : DFF Port Map(D => M(1), Load => Valid, clk => clk, Q => Q_tmp(1));
	DFF0 : DFF Port Map(D => M(0), Load => Valid, clk => clk, Q => Q_tmp(0));


end Behavioral;

Lab 06/ShiftRegister4B/ShiftRegister4B_tb.vhd

LIBRARY ieee;
USE ieee.std_logic_1164.ALL;

ENTITY ShiftRegister4B_tb IS
END ShiftRegister4B_tb;
 
ARCHITECTURE behavior OF ShiftRegister4B_tb IS 
 
    -- Component Declaration for the Unit Under Test (UUT)
 
    COMPONENT ShiftRegister4B
    PORT(
         Reset : IN  std_logic;
         Load : IN  std_logic;
         L : IN  std_logic;
         R : IN  std_logic;
         D : IN  std_logic_vector(3 downto 0);
         Q : OUT  std_logic_vector(3 downto 0);
         clk :IN  std_logic
        );
    END COMPONENT;
    

   --Inputs
   signal Reset : std_logic := '1';
   signal Load : std_logic := '0';
   signal L : std_logic := '0';
   signal R : std_logic := '0';
   signal D : std_logic_vector(3 downto 0) := (others => '0');

 	--Outputs
   signal Q : std_logic_vector(3 downto 0);
   signal clk : std_logic;

   -- Clock period definitions
   constant clk_period : time := 10 ns;
 
BEGIN
 
	-- Instantiate the Unit Under Test (UUT)
   uut: ShiftRegister4B PORT MAP (
          Reset => Reset,
          Load => Load,
          L => L,
          R => R,
          D => D,
          Q => Q,
          clk => clk
        );

   -- Clock process definitions
   clk_process :process
   begin
		clk <= '0';
		wait for clk_period/2;
		clk <= '1';
		wait for clk_period/2;
   end process;
 

   -- Stimulus process
   stim_proc: process
   begin		
      -- hold reset state for 100 ns.
      wait for 100 ns;
		Reset <= '0';
		D <= "0110";
		Load <= '1';
		wait for 40 ns;
		
		Load <= '0';
		L <= '1';

      wait for clk_period*10;

      -- insert stimulus here 

      wait;
   end process;

END;

Lab 6/ShiftRegister4B/out.vcd
$date
  Sun Apr 21 21:41:35 2024
$end
$version
  GHDL v0
$end
$timescale
  1 fs
$end
$scope module standard $end
$upscope $end
$scope module std_logic_1164 $end
$upscope $end
$scope module shiftregister4b_tb $end
$var reg 1 ! reset $end
$var reg 1 " load $end
$var reg 1 # l $end
$var reg 1 $ r $end
$var reg 4 % d[3:0] $end
$var reg 4 & q[3:0] $end
$var reg 1 ' clk $end
$scope module uut $end
$var reg 1 ( reset $end
$var reg 1 ) load $end
$var reg 1 * l $end
$var reg 1 + r $end
$var reg 4 , d[3:0] $end
$var reg 4 - q[3:0] $end
$var reg 1 . clk $end
$var reg 4 / m[3:0] $end
$var reg 4 0 q_tmp[3:0] $end
$var reg 2 1 p[1:0] $end
$var reg 1 2 valid $end
$scope module priorityencoder1 $end
$var reg 4 3 i[3:0] $end
$var reg 2 4 o[1:0] $end
$var reg 1 5 v $end
$upscope $end
$scope module mux3 $end
$var reg 4 6 i[3:0] $end
$var reg 2 7 s[1:0] $end
$var reg 1 8 o $end
$var reg 4 9 w[3:0] $end
$upscope $end
$scope module mux2 $end
$var reg 4 : i[3:0] $end
$var reg 2 ; s[1:0] $end
$var reg 1 < o $end
$var reg 4 = w[3:0] $end
$upscope $end
$scope module mux1 $end
$var reg 4 > i[3:0] $end
$var reg 2 ? s[1:0] $end
$var reg 1 @ o $end
$var reg 4 A w[3:0] $end
$upscope $end
$scope module mux0 $end
$var reg 4 B i[3:0] $end
$var reg 2 C s[1:0] $end
$var reg 1 D o $end
$var reg 4 E w[3:0] $end
$upscope $end
$scope module dff3 $end
$var reg 1 F d $end
$var reg 1 G load $end
$var reg 1 H clk $end
$var reg 1 I q $end
$upscope $end
$scope module dff2 $end
$var reg 1 J d $end
$var reg 1 K load $end
$var reg 1 L clk $end
$var reg 1 M q $end
$upscope $end
$scope module dff1 $end
$var reg 1 N d $end
$var reg 1 O load $end
$var reg 1 P clk $end
$var reg 1 Q q $end
$upscope $end
$scope module dff0 $end
$var reg 1 R d $end
$var reg 1 S load $end
$var reg 1 T clk $end
$var reg 1 U q $end
$upscope $end
$upscope $end
$upscope $end
$enddefinitions $end
#0
1!
0"
0#
0$
b0000 %
bUUUU &
0'
1(
0)
0*
0+
b0000 ,
bUUUU -
0.
b0000 /
bUUUU 0
b00 1
12
b0001 3
b00 4
15
b0U00 6
b00 7
08
b0000 9
bUU00 :
b00 ;
0<
b0000 =
bUU00 >
b00 ?
0@
b0000 A
bU000 B
b00 C
0D
b0000 E
0F
1G
0H
UI
0J
1K
0L
UM
0N
1O
0P
UQ
0R
1S
0T
UU
#5000000
b0000 &
1'
b0000 -
1.
b0000 0
b0000 6
b0000 :
b0000 >
b0000 B
1H
0I
1L
0M
1P
0Q
1T
0U
#10000000
0'
0.
0H
0L
0P
0T
#15000000
1'
1.
1H
1L
1P
1T
#20000000
0'
0.
0H
0L
0P
0T
#25000000
1'
1.
1H
1L
1P
1T
#30000000
0'
0.
0H
0L
0P
0T
#35000000
1'
1.
1H
1L
1P
1T
#40000000
0'
0.
0H
0L
0P
0T
#45000000
1'
1.
1H
1L
1P
1T
#50000000
0'
0.
0H
0L
0P
0T
#55000000
1'
1.
1H
1L
1P
1T
#60000000
0'
0.
0H
0L
0P
0T
#65000000
1'
1.
1H
1L
1P
1T
#70000000
0'
0.
0H
0L
0P
0T
#75000000
1'
1.
1H
1L
1P
1T
#80000000
0'
0.
0H
0L
0P
0T
#85000000
1'
1.
1H
1L
1P
1T
#90000000
0'
0.
0H
0L
0P
0T
#95000000
1'
1.
1H
1L
1P
1T
#100000000
0!
1"
b0110 %
0'
0(
1)
b0110 ,
0.
b0110 /
b01 1
b0010 3
b01 4
b01 7
b0010 :
b01 ;
1<
b0010 =
b0010 >
b01 ?
1@
b0010 A
b01 C
0H
1J
0L
1N
0P
0T
#105000000
b0110 &
1'
b0110 -
1.
b0110 0
b0100 6
b0110 :
b1010 >
b1000 B
1H
1L
1M
1P
1Q
1T
#110000000
0'
0.
0H
0L
0P
0T
#115000000
1'
1.
1H
1L
1P
1T
#120000000
0'
0.
0H
0L
0P
0T
#125000000
1'
1.
1H
1L
1P
1T
#130000000
0'
0.
0H
0L
0P
0T
#135000000
1'
1.
1H
1L
1P
1T
#140000000
0"
1#
0'
0)
1*
0.
b1100 /
b10 1
b0100 3
b10 4
b10 7
18
b0100 9
b10 ;
b0100 =
b10 ?
0@
b0000 A
b10 C
1F
0H
0L
0N
0P
0T
#145000000
b1100 &
1'
b1100 -
1.
b1000 /
b1100 0
b1010 :
0<
b0000 =
b0000 B
1H
1I
0J
1L
1P
0Q
1T
#150000000
0'
0.
0H
0L
0P
0T
#155000000
b1000 &
1'
b1000 -
1.
b0000 /
b1000 0
b0000 6
08
b0000 9
b0010 >
0F
1H
1L
0M
1P
1T
#160000000
0'
0.
0H
0L
0P
0T
#165000000
b0000 &
1'
b0000 -
1.
b0000 0
b0010 :
1H
0I
1L
1P
1T
